audioclipextractor/__init__.py
audioclipextractor/core.py
audioclipextractor/parser.py
audioclipextractor/scripts/__init__.py
audioclipextractor/scripts/main.py
tests/__init__.py
tests/constants.py
tests/test_cli.py
tests/test_core.py
tests/test_parser.py
audioclipextractor-0.3.0.dist-info/LICENSE.txt
audioclipextractor-0.3.0.dist-info/METADATA
audioclipextractor-0.3.0.dist-info/WHEEL
audioclipextractor-0.3.0.dist-info/entry_points.txt
audioclipextractor-0.3.0.dist-info/top_level.txt
audioclipextractor-0.3.0.dist-info/RECORD
