Metadata-Version: 2.1
Name: audioclipextractor
Version: 0.3.0
Summary: Easily extract multiple clips from audio files
Home-page: https://github.com/TiagoBras/audio-clip-extractor
Author: Tiago Bras
Author-email: tiagodsbras@gmail.com
License: MIT
Download-URL: https://github.com/TiagoBras/audio-clip-extractor/tarball/v0.3.0
Platform: UNKNOWN
Classifier: Development Status :: 3 - Alpha
Classifier: Environment :: Console
Classifier: Intended Audience :: Developers
Classifier: Intended Audience :: End Users/Desktop
Classifier: License :: OSI Approved :: MIT License
Classifier: Natural Language :: English
Classifier: Operating System :: MacOS
Classifier: Operating System :: Microsoft :: Windows
Classifier: Programming Language :: Python :: 2.7
Classifier: Programming Language :: Python :: 3.0
Classifier: Programming Language :: Python :: 3.1
Classifier: Programming Language :: Python :: 3.2
Classifier: Programming Language :: Python :: 3.3
Classifier: Programming Language :: Python :: 3.4
Classifier: Programming Language :: Python :: 3.5
Classifier: Topic :: Multimedia :: Sound/Audio :: Conversion
Classifier: Topic :: Utilities
